kafka_admin_service/__init__.py
kafka_admin_service/server.py
kafka_admin_service/service.py
kafka_admin_service-0.2.19.dist-info/licenses/LICENSE
kafka_admin_service-0.2.19.dist-info/METADATA
kafka_admin_service-0.2.19.dist-info/WHEEL
kafka_admin_service-0.2.19.dist-info/entry_points.txt
kafka_admin_service-0.2.19.dist-info/top_level.txt
kafka_admin_service-0.2.19.dist-info/RECORD
