Metadata-Version: 2.4
Name: kafka-admin-service
Version: 0.2.19
Summary: KAFKA管理类，提供用户创建、删除、列表查询、修改密码，提供主题创建、删除、列表查询，提供权限创建、删除、列表查询等基础管理功能。
Author: rRR0VrFP
Maintainer: rRR0VrFP
License: MIT
Keywords: kafka admin service,kafka admin client
Classifier: Development Status :: 5 - Production/Stable
Classifier: Intended Audience :: Developers
Classifier: Topic :: Software Development :: Libraries :: Python Modules
Classifier: License :: OSI Approved :: MIT License
Classifier: Programming Language :: Python :: 3
Classifier: Programming Language :: Python :: 3 :: Only
License-File: LICENSE
Requires-Dist: scramp
Requires-Dist: xmlrpcutils
Requires-Dist: fastutils>=0.42.13
Dynamic: author
Dynamic: classifier
Dynamic: description
Dynamic: description-content-type
Dynamic: keywords
Dynamic: license
Dynamic: license-file
Dynamic: maintainer
Dynamic: requires-dist
Dynamic: summary
